[{"fipscode":null,"level":"state","polid":"63126","polnum":"49283","precinctsreporting":2566,"precinctsreportingpct":1,"precinctstotal":2566,"raceid":"47225","statepostal":"VA","votecount":1040972,"votepct":0.47394,"winner":true},{"fipscode":null,"level":"state","polid":"63881","polnum":"49277","precinctsreporting":2566,"precinctsreportingpct":1,"precinctstotal":2566,"raceid":"47225","statepostal":"VA","votecount":1021873,"votepct":0.465244,"winner":false},{"fipscode":null,"level":"state","polid":"65898","polnum":"49354","precinctsreporting":2566,"precinctsreportingpct":1,"precinctstotal":2566,"raceid":"47225","statepostal":"VA","votecount":133577,"votepct":0.060816,"winner":false},{"fipscode":"51001","level":"county","polid":"63126","polnum":"49283","precinctsreporting":17,"precinctsreportingpct":1,"precinctstotal":17,"raceid":"47225","statepostal":"VA","votecount":5295,"votepct":0.562759,"winner":true},{"fipscode":"51001","level":"county","polid":"63881","polnum":"49277","precinctsreporting":17,"precinctsreportingpct":1,"precinctstotal":17,"raceid":"47225","statepostal":"VA","votecount":3746,"votepct":0.398129,"winner":false},{"fipscode":"51001","level":"county","polid":"65898","polnum":"49354","precinctsreporting":17,"precinctsreportingpct":1,"precinctstotal":17,"raceid":"47225","statepostal":"VA","votecount":368,"votepct":0.039111,"winner":false},{"fipscode":"51003","level":"county","polid":"63126","polnum":"49283","precinctsreporting":29,"precinctsreportingpct":1,"precinctstotal":29,"raceid":"47225","statepostal":"VA","votecount":11158,"votepct":0.37399,"winner":true},{"fipscode":"51003","level":"county","polid":"63881","polnum":"49277","precinctsreporting":29,"precinctsreportingpct":1,"precinctstotal":29,"raceid":"47225","statepostal":"VA","votecount":15857,"votepct":0.53149,"winner":false},{"fipscode":"51003","level":"county","polid":"65898","polnum":"49354","precinctsreporting":29,"precinctsreportingpct":1,"precinctstotal":29,"raceid":"47225","statepostal":"VA","votecount":2820,"votepct":0.09452,"winner":false},{"fipscode":"51005","level":"county","polid":"63126","polnum":"49283","precinctsreporting":13,"precinctsreportingpct":1,"precinctstotal":13,"raceid":"47225","statepostal":"VA","votecount":2134,"votepct":0.510526,"winner":true},{"fipscode":"51005","level":"county","polid":"63881","polnum":"49277","precinctsreporting":13,"precinctsreportingpct":1,"precinctstotal":13,"raceid":"47225","statepostal":"VA","votecount":1551,"votepct":0.371053,"winner":false},{"fipscode":"51005","level":"county","polid":"65898","polnum":"49354","precinctsreporting":13,"precinctsreportingpct":1,"precinctstotal":13,"raceid":"47225","statepostal":"VA","votecount":495,"votepct":0.118421,"winner":false},{"fipscode":"51007","level":"county","polid":"63126","polnum":"49283","precinctsreporting":6,"precinctsreportingpct":1,"precinctstotal":6,"raceid":"47225","statepostal":"VA","votecount":2376,"votepct":0.651137,"winner":true},{"fipscode":"51007","level":"county","polid":"63881","polnum":"49277","precinctsreporting":6,"precinctsreportingpct":1,"precinctstotal":6,"raceid":"47225","statepostal":"VA","votecount":1051,"votepct":0.288024,"winner":false},{"fipscode":"51007","level":"county","polid":"65898","polnum":"49354","precinctsreporting":6,"precinctsreportingpct":1,"precinctstotal":6,"raceid":"47225","statepostal":"VA","votecount":222,"votepct":0.060839,"winner":false},{"fipscode":"51009","level":"county","polid":"63126","polnum":"49283","precinctsreporting":12,"precinctsreportingpct":1,"precinctstotal":12,"raceid":"47225","statepostal":"VA","votecount":5259,"votepct":0.629368,"winner":true},{"fipscode":"51009","level":"county","polid":"63881","polnum":"49277","precinctsreporting":12,"precinctsreportingpct":1,"precinctstotal":12,"raceid":"47225","statepostal":"VA","votecount":2623,"votepct":0.313906,"winner":false},{"fipscode":"51009","level":"county","polid":"65898","polnum":"49354","precinctsreporting":12,"precinctsreportingpct":1,"precinctstotal":12,"raceid":"47225","statepostal":"VA","votecount":474,"votepct":0.056726,"winner":false},{"fipscode":"51011","level":"county","polid":"63126","polnum":"49283","precinctsreporting":10,"precinctsreportingpct":1,"precinctstotal":10,"raceid":"47225","statepostal":"VA","votecount":3045,"votepct":0.708799,"winner":true},{"fipscode":"51011","level":"county","polid":"63881","polnum":"49277","precinctsreporting":10,"precinctsreportingpct":1,"precinctstotal":10,"raceid":"47225","statepostal":"VA","votecount":985,"votepct":0.229283,"winner":false},{"fipscode":"51011","level":"county","polid":"65898","polnum":"49354","precinctsreporting":10,"precinctsreportingpct":1,"precinctstotal":10,"raceid":"47225","statepostal":"VA","votecount":266,"votepct":0.061918,"winner":false},{"fipscode":"51013","level":"county","polid":"63126","polnum":"49283","precinctsreporting":55,"precinctsreportingpct":1,"precinctstotal":55,"raceid":"47225","statepostal":"VA","votecount":15968,"votepct":0.240906,"winner":true},{"fipscode":"51013","level":"county","polid":"63881","polnum":"49277","precinctsreporting":55,"precinctsreportingpct":1,"precinctstotal":55,"raceid":"47225","statepostal":"VA","votecount":46815,"votepct":0.70629,"winner":false},{"fipscode":"51013","level":"county","polid":"65898","polnum":"49354","precinctsreporting":55,"precinctsreportingpct":1,"precinctstotal":55,"raceid":"47225","statepostal":"VA","votecount":3500,"votepct":0.052804,"winner":false},{"fipscode":"51015","level":"county","polid":"63126","polnum":"49283","precinctsreporting":26,"precinctsreportingpct":1,"precinctstotal":26,"raceid":"47225","statepostal":"VA","votecount":13394,"votepct":0.705765,"winner":true},{"fipscode":"51015","level":"county","polid":"63881","polnum":"49277","precinctsreporting":26,"precinctsreportingpct":1,"precinctstotal":26,"raceid":"47225","statepostal":"VA","votecount":4388,"votepct":0.231215,"winner":false},{"fipscode":"51015","level":"county","polid":"65898","polnum":"49354","precinctsreporting":26,"precinctsreportingpct":1,"precinctstotal":26,"raceid":"47225","statepostal":"VA","votecount":1196,"votepct":0.06302,"winner":false},{"fipscode":"51017","level":"county","polid":"63126","polnum":"49283","precinctsreporting":8,"precinctsreportingpct":1,"precinctstotal":8,"raceid":"47225","statepostal":"VA","votecount":767,"votepct":0.597352,"winner":true},{"fipscode":"51017","level":"county","polid":"63881","polnum":"49277","precinctsreporting":8,"precinctsreportingpct":1,"precinctstotal":8,"raceid":"47225","statepostal":"VA","votecount":386,"votepct":0.300623,"winner":false},{"fipscode":"51017","level":"county","polid":"65898","polnum":"49354","precinctsreporting":8,"precinctsreportingpct":1,"precinctstotal":8,"raceid":"47225","statepostal":"VA","votecount":131,"votepct":0.102025,"winner":false},{"fipscode":"51019","level":"county","polid":"63126","polnum":"49283","precinctsreporting":32,"precinctsreportingpct":1,"precinctstotal":32,"raceid":"47225","statepostal":"VA","votecount":15854,"votepct":0.716274,"winner":true},{"fipscode":"51019","level":"county","polid":"63881","polnum":"49277","precinctsreporting":32,"precinctsreportingpct":1,"precinctstotal":32,"raceid":"47225","statepostal":"VA","votecount":4772,"votepct":0.215596,"winner":false},{"fipscode":"51019","level":"county","polid":"65898","polnum":"49354","precinctsreporting":32,"precinctsreportingpct":1,"precinctstotal":32,"raceid":"47225","statepostal":"VA","votecount":1508,"votepct":0.06813,"winner":false},{"fipscode":"51021","level":"county","polid":"63126","polnum":"49283","precinctsreporting":8,"precinctsreportingpct":1,"precinctstotal":8,"raceid":"47225","statepostal":"VA","votecount":1323,"votepct":0.73337,"winner":true},{"fipscode":"51021","level":"county","polid":"63881","polnum":"49277","precinctsreporting":8,"precinctsreportingpct":1,"precinctstotal":8,"raceid":"47225","statepostal":"VA","votecount":337,"votepct":0.186807,"winner":false},{"fipscode":"51021","level":"county","polid":"65898","polnum":"49354","precinctsreporting":8,"precinctsreportingpct":1,"precinctstotal":8,"raceid":"47225","statepostal":"VA","votecount":144,"votepct":0.079823,"winner":false},{"fipscode":"51023","level":"county","polid":"63126","polnum":"49283","precinctsreporting":11,"precinctsreportingpct":1,"precinctstotal":11,"raceid":"47225","statepostal":"VA","votecount":6577,"votepct":0.690281,"winner":true},{"fipscode":"51023","level":"county","polid":"63881","polnum":"49277","precinctsreporting":11,"precinctsreportingpct":1,"precinctstotal":11,"raceid":"47225","statepostal":"VA","votecount":2227,"votepct":0.233732,"winner":false},{"fipscode":"51023","level":"county","polid":"65898","polnum":"49354","precinctsreporting":11,"precinctsreportingpct":1,"precinctstotal":11,"raceid":"47225","statepostal":"VA","votecount":724,"votepct":0.075987,"winner":false},{"fipscode":"51025","level":"county","polid":"63126","polnum":"49283","precinctsreporting":14,"precinctsreportingpct":1,"precinctstotal":14,"raceid":"47225","statepostal":"VA","votecount":1646,"votepct":0.382346,"winner":true},{"fipscode":"51025","level":"county","polid":"63881","polnum":"49277","precinctsreporting":14,"precinctsreportingpct":1,"precinctstotal":14,"raceid":"47225","statepostal":"VA","votecount":2480,"votepct":0.576074,"winner":false},{"fipscode":"51025","level":"county","polid":"65898","polnum":"49354","precinctsreporting":14,"precinctsreportingpct":1,"precinctstotal":14,"raceid":"47225","statepostal":"VA","votecount":179,"votepct":0.04158,"winner":false},{"fipscode":"51027","level":"county","polid":"63126","polnum":"49283","precinctsreporting":18,"precinctsreportingpct":1,"precinctstotal":18,"raceid":"47225","statepostal":"VA","votecount":4207,"votepct":0.688431,"winner":true},{"fipscode":"51027","level":"county","polid":"63881","polnum":"49277","precinctsreporting":18,"precinctsreportingpct":1,"precinctstotal":18,"raceid":"47225","statepostal":"VA","votecount":1753,"votepct":0.28686,"winner":false},{"fipscode":"51027","level":"county","polid":"65898","polnum":"49354","precinctsreporting":18,"precinctsreportingpct":1,"precinctstotal":18,"raceid":"47225","statepostal":"VA","votecount":151,"votepct":0.02471,"winner":false},{"fipscode":"51029","level":"county","polid":"63126","polnum":"49283","precinctsreporting":11,"precinctsreportingpct":1,"precinctstotal":11,"raceid":"47225","statepostal":"VA","votecount":2093,"votepct":0.51362,"winner":true},{"fipscode":"51029","level":"county","polid":"63881","polnum":"49277","precinctsreporting":11,"precinctsreportingpct":1,"precinctstotal":11,"raceid":"47225","statepostal":"VA","votecount":1704,"votepct":0.41816,"winner":false},{"fipscode":"51029","level":"county","polid":"65898","polnum":"49354","precinctsreporting":11,"precinctsreportingpct":1,"precinctstotal":11,"raceid":"47225","statepostal":"VA","votecount":278,"votepct":0.068221,"winner":false},{"fipscode":"51031","level":"county","polid":"63126","polnum":"49283","precinctsreporting":17,"precinctsreportingpct":1,"precinctstotal":17,"raceid":"47225","statepostal":"VA","votecount":10954,"votepct":0.735662,"winner":true},{"fipscode":"51031","level":"county","polid":"63881","polnum":"49277","precinctsreporting":17,"precinctsreportingpct":1,"precinctstotal":17,"raceid":"47225","statepostal":"VA","votecount":3161,"votepct":0.21229,"winner":false},{"fipscode":"51031","level":"county","polid":"65898","polnum":"49354","precinctsreporting":17,"precinctsreportingpct":1,"precinctstotal":17,"raceid":"47225","statepostal":"VA","votecount":775,"votepct":0.052048,"winner":false},{"fipscode":"51033","level":"county","polid":"63126","polnum":"49283","precinctsreporting":13,"precinctsreportingpct":1,"precinctstotal":13,"raceid":"47225","statepostal":"VA","votecount":3604,"votepct":0.457883,"winner":true},{"fipscode":"51033","level":"county","polid":"63881","polnum":"49277","precinctsreporting":13,"precinctsreportingpct":1,"precinctstotal":13,"raceid":"47225","statepostal":"VA","votecount":3758,"votepct":0.477449,"winner":false},{"fipscode":"51033","level":"county","polid":"65898","polnum":"49354","precinctsreporting":13,"precinctsreportingpct":1,"precinctstotal":13,"raceid":"47225","statepostal":"VA","votecount":509,"votepct":0.064668,"winner":false},{"fipscode":"51035","level":"county","polid":"63126","polnum":"49283","precinctsreporting":19,"precinctsreportingpct":1,"precinctstotal":19,"raceid":"47225","statepostal":"VA","votecount":5131,"votepct":0.671949,"winner":true},{"fipscode":"51035","level":"county","polid":"63881","polnum":"49277","precinctsreporting":19,"precinctsreportingpct":1,"precinctstotal":19,"raceid":"47225","statepostal":"VA","votecount":1939,"votepct":0.253929,"winner":false},{"fipscode":"51035","level":"county","polid":"65898","polnum":"49354","precinctsreporting":19,"precinctsreportingpct":1,"precinctstotal":19,"raceid":"47225","statepostal":"VA","votecount":566,"votepct":0.074123,"winner":false},{"fipscode":"51036","level":"county","polid":"63126","polnum":"49283","precinctsreporting":4,"precinctsreportingpct":1,"precinctstotal":4,"raceid":"47225","statepostal":"VA","votecount":753,"votepct":0.343365,"winner":true},{"fipscode":"51036","level":"county","polid":"63881","polnum":"49277","precinctsreporting":4,"precinctsreportingpct":1,"precinctstotal":4,"raceid":"47225","statepostal":"VA","votecount":1311,"votepct":0.597811,"winner":false},{"fipscode":"51036","level":"county","polid":"65898","polnum":"49354","precinctsreporting":4,"precinctsreportingpct":1,"precinctstotal":4,"raceid":"47225","statepostal":"VA","votecount":129,"votepct":0.058824,"winner":false},{"fipscode":"51037","level":"county","polid":"63126","polnum":"49283","precinctsreporting":8,"precinctsreportingpct":1,"precinctstotal":8,"raceid":"47225","statepostal":"VA","votecount":1906,"votepct":0.587365,"winner":true},{"fipscode":"51037","level":"county","polid":"63881","polnum":"49277","precinctsreporting":8,"precinctsreportingpct":1,"precinctstotal":8,"raceid":"47225","statepostal":"VA","votecount":1125,"votepct":0.346687,"winner":false},{"fipscode":"51037","level":"county","polid":"65898","polnum":"49354","precinctsreporting":8,"precinctsreportingpct":1,"precinctstotal":8,"raceid":"47225","statepostal":"VA","votecount":214,"votepct":0.065948,"winner":false},{"fipscode":"51043","level":"county","polid":"63126","polnum":"49283","precinctsreporting":8,"precinctsreportingpct":1,"precinctstotal":8,"raceid":"47225","statepostal":"VA","votecount":2319,"votepct":0.54539,"winner":true},{"fipscode":"51043","level":"county","polid":"63881","polnum":"49277","precinctsreporting":8,"precinctsreportingpct":1,"precinctstotal":8,"raceid":"47225","statepostal":"VA","votecount":1680,"votepct":0.395108,"winner":false},{"fipscode":"51043","level":"county","polid":"65898","polnum":"49354","precinctsreporting":8,"precinctsreportingpct":1,"precinctstotal":8,"raceid":"47225","statepostal":"VA","votecount":253,"votepct":0.059501,"winner":false},{"fipscode":"51045","level":"county","polid":"63126","polnum":"49283","precinctsreporting":8,"precinctsreportingpct":1,"precinctstotal":8,"raceid":"47225","statepostal":"VA","votecount":1039,"votepct":0.6738,"winner":true},{"fipscode":"51045","level":"county","polid":"63881","polnum":"49277","precinctsreporting":8,"precinctsreportingpct":1,"precinctstotal":8,"raceid":"47225","statepostal":"VA","votecount":344,"votepct":0.223087,"winner":false},{"fipscode":"51045","level":"county","polid":"65898","polnum":"49354","precinctsreporting":8,"precinctsreportingpct":1,"precinctstotal":8,"raceid":"47225","statepostal":"VA","votecount":159,"votepct":0.103113,"winner":false},{"fipscode":"51047","level":"county","polid":"63126","polnum":"49283","precinctsreporting":16,"precinctsreportingpct":1,"precinctstotal":16,"raceid":"47225","statepostal":"VA","votecount":7858,"votepct":0.63325,"winner":true},{"fipscode":"51047","level":"county","polid":"63881","polnum":"49277","precinctsreporting":16,"precinctsreportingpct":1,"precinctstotal":16,"raceid":"47225","statepostal":"VA","votecount":3945,"votepct":0.317914,"winner":false},{"fipscode":"51047","level":"county","polid":"65898","polnum":"49354","precinctsreporting":16,"precinctsreportingpct":1,"precinctstotal":16,"raceid":"47225","statepostal":"VA","votecount":606,"votepct":0.048836,"winner":false},{"fipscode":"51049","level":"county","polid":"63126","polnum":"49283","precinctsreporting":6,"precinctsreportingpct":1,"precinctstotal":6,"raceid":"47225","statepostal":"VA","votecount":1417,"votepct":0.524232,"winner":true},{"fipscode":"51049","level":"county","polid":"63881","polnum":"49277","precinctsreporting":6,"precinctsreportingpct":1,"precinctstotal":6,"raceid":"47225","statepostal":"VA","votecount":1056,"votepct":0.390677,"winner":false},{"fipscode":"51049","level":"county","polid":"65898","polnum":"49354","precinctsreporting":6,"precinctsreportingpct":1,"precinctstotal":6,"raceid":"47225","statepostal":"VA","votecount":230,"votepct":0.085091,"winner":false},{"fipscode":"51051","level":"county","polid":"63126","polnum":"49283","precinctsreporting":11,"precinctsreportingpct":1,"precinctstotal":11,"raceid":"47225","statepostal":"VA","votecount":2662,"votepct":0.653893,"winner":true},{"fipscode":"51051","level":"county","polid":"63881","polnum":"49277","precinctsreporting":11,"precinctsreportingpct":1,"precinctstotal":11,"raceid":"47225","statepostal":"VA","votecount":1315,"votepct":0.323016,"winner":false},{"fipscode":"51051","level":"county","polid":"65898","polnum":"49354","precinctsreporting":11,"precinctsreportingpct":1,"precinctstotal":11,"raceid":"47225","statepostal":"VA","votecount":94,"votepct":0.02309,"winner":false},{"fipscode":"51053","level":"county","polid":"63126","polnum":"49283","precinctsreporting":14,"precinctsreportingpct":1,"precinctstotal":14,"raceid":"47225","statepostal":"VA","votecount":3707,"votepct":0.491971,"winner":true},{"fipscode":"51053","level":"county","polid":"63881","polnum":"49277","precinctsreporting":14,"precinctsreportingpct":1,"precinctstotal":14,"raceid":"47225","statepostal":"VA","votecount":3278,"votepct":0.435036,"winner":false},{"fipscode":"51053","level":"county","polid":"65898","polnum":"49354","precinctsreporting":14,"precinctsreportingpct":1,"precinctstotal":14,"raceid":"47225","statepostal":"VA","votecount":550,"votepct":0.072993,"winner":false},{"fipscode":"51057","level":"county","polid":"63126","polnum":"49283","precinctsreporting":5,"precinctsreportingpct":1,"precinctstotal":5,"raceid":"47225","statepostal":"VA","votecount":1520,"votepct":0.503145,"winner":true},{"fipscode":"51057","level":"county","polid":"63881","polnum":"49277","precinctsreporting":5,"precinctsreportingpct":1,"precinctstotal":5,"raceid":"47225","statepostal":"VA","votecount":1290,"votepct":0.427011,"winner":false},{"fipscode":"51057","level":"county","polid":"65898","polnum":"49354","precinctsreporting":5,"precinctsreportingpct":1,"precinctstotal":5,"raceid":"47225","statepostal":"VA","votecount":211,"votepct":0.069844,"winner":false},{"fipscode":"51061","level":"county","polid":"63126","polnum":"49283","precinctsreporting":21,"precinctsreportingpct":1,"precinctstotal":21,"raceid":"47225","statepostal":"VA","votecount":12430,"votepct":0.63167,"winner":true},{"fipscode":"51061","level":"county","polid":"63881","polnum":"49277","precinctsreporting":21,"precinctsreportingpct":1,"precinctstotal":21,"raceid":"47225","statepostal":"VA","votecount":6419,"votepct":0.326202,"winner":false},{"fipscode":"51061","level":"county","polid":"65898","polnum":"49354","precinctsreporting":21,"precinctsreportingpct":1,"precinctstotal":21,"raceid":"47225","statepostal":"VA","votecount":829,"votepct":0.042128,"winner":false},{"fipscode":"51063","level":"county","polid":"63126","polnum":"49283","precinctsreporting":6,"precinctsreportingpct":1,"precinctstotal":6,"raceid":"47225","statepostal":"VA","votecount":2562,"votepct":0.596091,"winner":true},{"fipscode":"51063","level":"county","polid":"63881","polnum":"49277","precinctsreporting":6,"precinctsreportingpct":1,"precinctstotal":6,"raceid":"47225","statepostal":"VA","votecount":1360,"votepct":0.316426,"winner":false},{"fipscode":"51063","level":"county","polid":"65898","polnum":"49354","precinctsreporting":6,"precinctsreportingpct":1,"precinctstotal":6,"raceid":"47225","statepostal":"VA","votecount":376,"votepct":0.087483,"winner":false},{"fipscode":"51065","level":"county","polid":"63126","polnum":"49283","precinctsreporting":6,"precinctsreportingpct":1,"precinctstotal":6,"raceid":"47225","statepostal":"VA","votecount":3594,"votepct":0.501955,"winner":true},{"fipscode":"51065","level":"county","polid":"63881","polnum":"49277","precinctsreporting":6,"precinctsreportingpct":1,"precinctstotal":6,"raceid":"47225","statepostal":"VA","votecount":2913,"votepct":0.406844,"winner":false},{"fipscode":"51065","level":"county","polid":"65898","polnum":"49354","precinctsreporting":6,"precinctsreportingpct":1,"precinctstotal":6,"raceid":"47225","statepostal":"VA","votecount":653,"votepct":0.091201,"winner":false},{"fipscode":"51067","level":"county","polid":"63126","polnum":"49283","precinctsreporting":24,"precinctsreportingpct":1,"precinctstotal":24,"raceid":"47225","statepostal":"VA","votecount":9061,"votepct":0.633681,"winner":true},{"fipscode":"51067","level":"county","polid":"63881","polnum":"49277","precinctsreporting":24,"precinctsreportingpct":1,"precinctstotal":24,"raceid":"47225","statepostal":"VA","votecount":3979,"votepct":0.278271,"winner":false},{"fipscode":"51067","level":"county","polid":"65898","polnum":"49354","precinctsreporting":24,"precinctsreportingpct":1,"precinctstotal":24,"raceid":"47225","statepostal":"VA","votecount":1259,"votepct":0.088048,"winner":false},{"fipscode":"51069","level":"county","polid":"63126","polnum":"49283","precinctsreporting":22,"precinctsreportingpct":1,"precinctstotal":22,"raceid":"47225","statepostal":"VA","votecount":15086,"votepct":0.665373,"winner":true},{"fipscode":"51069","level":"county","polid":"63881","polnum":"49277","precinctsreporting":22,"precinctsreportingpct":1,"precinctstotal":22,"raceid":"47225","statepostal":"VA","votecount":6387,"votepct":0.281701,"winner":false},{"fipscode":"51069","level":"county","polid":"65898","polnum":"49354","precinctsreporting":22,"precinctsreportingpct":1,"precinctstotal":22,"raceid":"47225","statepostal":"VA","votecount":1200,"votepct":0.052926,"winner":false},{"fipscode":"51071","level":"county","polid":"63126","polnum":"49283","precinctsreporting":10,"precinctsreportingpct":1,"precinctstotal":10,"raceid":"47225","statepostal":"VA","votecount":2779,"votepct":0.614687,"winner":true},{"fipscode":"51071","level":"county","polid":"63881","polnum":"49277","precinctsreporting":10,"precinctsreportingpct":1,"precinctstotal":10,"raceid":"47225","statepostal":"VA","votecount":1315,"votepct":0.290865,"winner":false},{"fipscode":"51071","level":"county","polid":"65898","polnum":"49354","precinctsreporting":10,"precinctsreportingpct":1,"precinctstotal":10,"raceid":"47225","statepostal":"VA","votecount":427,"votepct":0.094448,"winner":false},{"fipscode":"51073","level":"county","polid":"63126","polnum":"49283","precinctsreporting":12,"precinctsreportingpct":1,"precinctstotal":12,"raceid":"47225","statepostal":"VA","votecount":6655,"votepct":0.619243,"winner":true},{"fipscode":"51073","level":"county","polid":"63881","polnum":"49277","precinctsreporting":12,"precinctsreportingpct":1,"precinctstotal":12,"raceid":"47225","statepostal":"VA","votecount":3317,"votepct":0.308644,"winner":false},{"fipscode":"51073","level":"county","polid":"65898","polnum":"49354","precinctsreporting":12,"precinctsreportingpct":1,"precinctstotal":12,"raceid":"47225","statepostal":"VA","votecount":775,"votepct":0.072113,"winner":false},{"fipscode":"51075","level":"county","polid":"63126","polnum":"49283","precinctsreporting":11,"precinctsreportingpct":1,"precinctstotal":11,"raceid":"47225","statepostal":"VA","votecount":4139,"votepct":0.596398,"winner":true},{"fipscode":"51075","level":"county","polid":"63881","polnum":"49277","precinctsreporting":11,"precinctsreportingpct":1,"precinctstotal":11,"raceid":"47225","statepostal":"VA","votecount":2202,"votepct":0.317291,"winner":false},{"fipscode":"51075","level":"county","polid":"65898","polnum":"49354","precinctsreporting":11,"precinctsreportingpct":1,"precinctstotal":11,"raceid":"47225","statepostal":"VA","votecount":599,"votepct":0.086311,"winner":false},{"fipscode":"51077","level":"county","polid":"63126","polnum":"49283","precinctsreporting":16,"precinctsreportingpct":1,"precinctstotal":16,"raceid":"47225","statepostal":"VA","votecount":2712,"votepct":0.663081,"winner":true},{"fipscode":"51077","level":"county","polid":"63881","polnum":"49277","precinctsreporting":16,"precinctsreportingpct":1,"precinctstotal":16,"raceid":"47225","statepostal":"VA","votecount":1086,"votepct":0.265526,"winner":false},{"fipscode":"51077","level":"county","polid":"65898","polnum":"49354","precinctsreporting":16,"precinctsreportingpct":1,"precinctstotal":16,"raceid":"47225","statepostal":"VA","votecount":292,"votepct":0.071394,"winner":false},{"fipscode":"51079","level":"county","polid":"63126","polnum":"49283","precinctsreporting":6,"precinctsreportingpct":1,"precinctstotal":6,"raceid":"47225","statepostal":"VA","votecount":3075,"votepct":0.593057,"winner":true},{"fipscode":"51079","level":"county","polid":"63881","polnum":"49277","precinctsreporting":6,"precinctsreportingpct":1,"precinctstotal":6,"raceid":"47225","statepostal":"VA","votecount":1592,"votepct":0.30704,"winner":false},{"fipscode":"51079","level":"county","polid":"65898","polnum":"49354","precinctsreporting":6,"precinctsreportingpct":1,"precinctstotal":6,"raceid":"47225","statepostal":"VA","votecount":518,"votepct":0.099904,"winner":false},{"fipscode":"51081","level":"county","polid":"63126","polnum":"49283","precinctsreporting":9,"precinctsreportingpct":1,"precinctstotal":9,"raceid":"47225","statepostal":"VA","votecount":960,"votepct":0.373977,"winner":true},{"fipscode":"51081","level":"county","polid":"63881","polnum":"49277","precinctsreporting":9,"precinctsreportingpct":1,"precinctstotal":9,"raceid":"47225","statepostal":"VA","votecount":1495,"votepct":0.582392,"winner":false},{"fipscode":"51081","level":"county","polid":"65898","polnum":"49354","precinctsreporting":9,"precinctsreportingpct":1,"precinctstotal":9,"raceid":"47225","statepostal":"VA","votecount":112,"votepct":0.043631,"winner":false},{"fipscode":"51083","level":"county","polid":"63126","polnum":"49283","precinctsreporting":21,"precinctsreportingpct":1,"precinctstotal":21,"raceid":"47225","statepostal":"VA","votecount":5470,"votepct":0.572355,"winner":true},{"fipscode":"51083","level":"county","polid":"63881","polnum":"49277","precinctsreporting":21,"precinctsreportingpct":1,"precinctstotal":21,"raceid":"47225","statepostal":"VA","votecount":3533,"votepct":0.369677,"winner":false},{"fipscode":"51083","level":"county","polid":"65898","polnum":"49354","precinctsreporting":21,"precinctsreportingpct":1,"precinctstotal":21,"raceid":"47225","statepostal":"VA","votecount":554,"votepct":0.057968,"winner":false},{"fipscode":"51085","level":"county","polid":"63126","polnum":"49283","precinctsreporting":37,"precinctsreportingpct":1,"precinctstotal":37,"raceid":"47225","statepostal":"VA","votecount":19345,"votepct":0.635074,"winner":true},{"fipscode":"51085","level":"county","polid":"63881","polnum":"49277","precinctsreporting":37,"precinctsreportingpct":1,"precinctstotal":37,"raceid":"47225","statepostal":"VA","votecount":7996,"votepct":0.2625,"winner":false},{"fipscode":"51085","level":"county","polid":"65898","polnum":"49354","precinctsreporting":37,"precinctsreportingpct":1,"precinctstotal":37,"raceid":"47225","statepostal":"VA","votecount":3120,"votepct":0.102426,"winner":false},{"fipscode":"51087","level":"county","polid":"63126","polnum":"49283","precinctsreporting":92,"precinctsreportingpct":1,"precinctstotal":92,"raceid":"47225","statepostal":"VA","votecount":36086,"votepct":0.414605,"winner":true},{"fipscode":"51087","level":"county","polid":"63881","polnum":"49277","precinctsreporting":92,"precinctsreportingpct":1,"precinctstotal":92,"raceid":"47225","statepostal":"VA","votecount":43257,"votepct":0.496996,"winner":false},{"fipscode":"51087","level":"county","polid":"65898","polnum":"49354","precinctsreporting":92,"precinctsreportingpct":1,"precinctstotal":92,"raceid":"47225","statepostal":"VA","votecount":7694,"votepct":0.088399,"winner":false},{"fipscode":"51089","level":"county","polid":"63126","polnum":"49283","precinctsreporting":25,"precinctsreportingpct":1,"precinctstotal":25,"raceid":"47225","statepostal":"VA","votecount":8676,"votepct":0.620867,"winner":true},{"fipscode":"51089","level":"county","polid":"63881","polnum":"49277","precinctsreporting":25,"precinctsreportingpct":1,"precinctstotal":25,"raceid":"47225","statepostal":"VA","votecount":4403,"votepct":0.315085,"winner":false},{"fipscode":"51089","level":"county","polid":"65898","polnum":"49354","precinctsreporting":25,"precinctsreportingpct":1,"precinctstotal":25,"raceid":"47225","statepostal":"VA","votecount":895,"votepct":0.064048,"winner":false},{"fipscode":"51091","level":"county","polid":"63126","polnum":"49283","precinctsreporting":6,"precinctsreportingpct":1,"precinctstotal":6,"raceid":"47225","statepostal":"VA","votecount":456,"votepct":0.635097,"winner":true},{"fipscode":"51091","level":"county","polid":"63881","polnum":"49277","precinctsreporting":6,"precinctsreportingpct":1,"precinctstotal":6,"raceid":"47225","statepostal":"VA","votecount":213,"votepct":0.296657,"winner":false},{"fipscode":"51091","level":"county","polid":"65898","polnum":"49354","precinctsreporting":6,"precinctsreportingpct":1,"precinctstotal":6,"raceid":"47225","statepostal":"VA","votecount":49,"votepct":0.068245,"winner":false},{"fipscode":"51093","level":"county","polid":"63126","polnum":"49283","precinctsreporting":15,"precinctsreportingpct":1,"precinctstotal":15,"raceid":"47225","statepostal":"VA","votecount":6160,"votepct":0.555455,"winner":true},{"fipscode":"51093","level":"county","polid":"63881","polnum":"49277","precinctsreporting":15,"precinctsreportingpct":1,"precinctstotal":15,"raceid":"47225","statepostal":"VA","votecount":4274,"votepct":0.385392,"winner":false},{"fipscode":"51093","level":"county","polid":"65898","polnum":"49354","precinctsreporting":15,"precinctsreportingpct":1,"precinctstotal":15,"raceid":"47225","statepostal":"VA","votecount":656,"votepct":0.059152,"winner":false},{"fipscode":"51095","level":"county","polid":"63126","polnum":"49283","precinctsreporting":20,"precinctsreportingpct":1,"precinctstotal":20,"raceid":"47225","statepostal":"VA","votecount":11966,"votepct":0.533982,"winner":true},{"fipscode":"51095","level":"county","polid":"63881","polnum":"49277","precinctsreporting":20,"precinctsreportingpct":1,"precinctstotal":20,"raceid":"47225","statepostal":"VA","votecount":8997,"votepct":0.40149,"winner":false},{"fipscode":"51095","level":"county","polid":"65898","polnum":"49354","precinctsreporting":20,"precinctsreportingpct":1,"precinctstotal":20,"raceid":"47225","statepostal":"VA","votecount":1446,"votepct":0.064528,"winner":false},{"fipscode":"51097","level":"county","polid":"63126","polnum":"49283","precinctsreporting":6,"precinctsreportingpct":1,"precinctstotal":6,"raceid":"47225","statepostal":"VA","votecount":998,"votepct":0.507372,"winner":true},{"fipscode":"51097","level":"county","polid":"63881","polnum":"49277","precinctsreporting":6,"precinctsreportingpct":1,"precinctstotal":6,"raceid":"47225","statepostal":"VA","votecount":841,"votepct":0.427555,"winner":false},{"fipscode":"51097","level":"county","polid":"65898","polnum":"49354","precinctsreporting":6,"precinctsreportingpct":1,"precinctstotal":6,"raceid":"47225","statepostal":"VA","votecount":128,"votepct":0.065074,"winner":false},{"fipscode":"51099","level":"county","polid":"63126","polnum":"49283","precinctsreporting":6,"precinctsreportingpct":1,"precinctstotal":6,"raceid":"47225","statepostal":"VA","votecount":4038,"votepct":0.618945,"winner":true},{"fipscode":"51099","level":"county","polid":"63881","polnum":"49277","precinctsreporting":6,"precinctsreportingpct":1,"precinctstotal":6,"raceid":"47225","statepostal":"VA","votecount":2118,"votepct":0.324647,"winner":false},{"fipscode":"51099","level":"county","polid":"65898","polnum":"49354","precinctsreporting":6,"precinctsreportingpct":1,"precinctstotal":6,"raceid":"47225","statepostal":"VA","votecount":368,"votepct":0.056407,"winner":false},{"fipscode":"51101","level":"county","polid":"63126","polnum":"49283","precinctsreporting":7,"precinctsreportingpct":1,"precinctstotal":7,"raceid":"47225","statepostal":"VA","votecount":2812,"votepct":0.594252,"winner":true},{"fipscode":"51101","level":"county","polid":"63881","polnum":"49277","precinctsreporting":7,"precinctsreportingpct":1,"precinctstotal":7,"raceid":"47225","statepostal":"VA","votecount":1443,"votepct":0.304945,"winner":false},{"fipscode":"51101","level":"county","polid":"65898","polnum":"49354","precinctsreporting":7,"precinctsreportingpct":1,"precinctstotal":7,"raceid":"47225","statepostal":"VA","votecount":477,"votepct":0.100803,"winner":false},{"fipscode":"51103","level":"county","polid":"63126","polnum":"49283","precinctsreporting":7,"precinctsreportingpct":1,"precinctstotal":7,"raceid":"47225","statepostal":"VA","votecount":1871,"votepct":0.545163,"winner":true},{"fipscode":"51103","level":"county","polid":"63881","polnum":"49277","precinctsreporting":7,"precinctsreportingpct":1,"precinctstotal":7,"raceid":"47225","statepostal":"VA","votecount":1310,"votepct":0.381702,"winner":false},{"fipscode":"51103","level":"county","polid":"65898","polnum":"49354","precinctsreporting":7,"precinctsreportingpct":1,"precinctstotal":7,"raceid":"47225","statepostal":"VA","votecount":251,"votepct":0.073135,"winner":false},{"fipscode":"51105","level":"county","polid":"63126","polnum":"49283","precinctsreporting":17,"precinctsreportingpct":1,"precinctstotal":17,"raceid":"47225","statepostal":"VA","votecount":4487,"votepct":0.751465,"winner":true},{"fipscode":"51105","level":"county","polid":"63881","polnum":"49277","precinctsreporting":17,"precinctsreportingpct":1,"precinctstotal":17,"raceid":"47225","statepostal":"VA","votecount":1321,"votepct":0.221236,"winner":false},{"fipscode":"51105","level":"county","polid":"65898","polnum":"49354","precinctsreporting":17,"precinctsreportingpct":1,"precinctstotal":17,"raceid":"47225","statepostal":"VA","votecount":163,"votepct":0.027299,"winner":false},{"fipscode":"51107","level":"county","polid":"63126","polnum":"49283","precinctsreporting":97,"precinctsreportingpct":1,"precinctstotal":97,"raceid":"47225","statepostal":"VA","votecount":45344,"votepct":0.469696,"winner":true},{"fipscode":"51107","level":"county","polid":"63881","polnum":"49277","precinctsreporting":97,"precinctsreportingpct":1,"precinctstotal":97,"raceid":"47225","statepostal":"VA","votecount":47111,"votepct":0.488,"winner":false},{"fipscode":"51107","level":"county","polid":"65898","polnum":"49354","precinctsreporting":97,"precinctsreportingpct":1,"precinctstotal":97,"raceid":"47225","statepostal":"VA","votecount":4084,"votepct":0.042304,"winner":false},{"fipscode":"51109","level":"county","polid":"63126","polnum":"49283","precinctsreporting":16,"precinctsreportingpct":1,"precinctstotal":16,"raceid":"47225","statepostal":"VA","votecount":5392,"votepct":0.571671,"winner":true},{"fipscode":"51109","level":"county","polid":"63881","polnum":"49277","precinctsreporting":16,"precinctsreportingpct":1,"precinctstotal":16,"raceid":"47225","statepostal":"VA","votecount":3144,"votepct":0.333333,"winner":false},{"fipscode":"51109","level":"county","polid":"65898","polnum":"49354","precinctsreporting":16,"precinctsreportingpct":1,"precinctstotal":16,"raceid":"47225","statepostal":"VA","votecount":896,"votepct":0.094996,"winner":false},{"fipscode":"51111","level":"county","polid":"63126","polnum":"49283","precinctsreporting":12,"precinctsreportingpct":1,"precinctstotal":12,"raceid":"47225","statepostal":"VA","votecount":1649,"votepct":0.532967,"winner":true},{"fipscode":"51111","level":"county","polid":"63881","polnum":"49277","precinctsreporting":12,"precinctsreportingpct":1,"precinctstotal":12,"raceid":"47225","statepostal":"VA","votecount":1225,"votepct":0.395928,"winner":false},{"fipscode":"51111","level":"county","polid":"65898","polnum":"49354","precinctsreporting":12,"precinctsreportingpct":1,"precinctstotal":12,"raceid":"47225","statepostal":"VA","votecount":220,"votepct":0.071105,"winner":false},{"fipscode":"51113","level":"county","polid":"63126","polnum":"49283","precinctsreporting":10,"precinctsreportingpct":1,"precinctstotal":10,"raceid":"47225","statepostal":"VA","votecount":2128,"votepct":0.586387,"winner":true},{"fipscode":"51113","level":"county","polid":"63881","polnum":"49277","precinctsreporting":10,"precinctsreportingpct":1,"precinctstotal":10,"raceid":"47225","statepostal":"VA","votecount":1190,"votepct":0.327914,"winner":false},{"fipscode":"51113","level":"county","polid":"65898","polnum":"49354","precinctsreporting":10,"precinctsreportingpct":1,"precinctstotal":10,"raceid":"47225","statepostal":"VA","votecount":311,"votepct":0.085699,"winner":false},{"fipscode":"51115","level":"county","polid":"63126","polnum":"49283","precinctsreporting":4,"precinctsreportingpct":1,"precinctstotal":4,"raceid":"47225","statepostal":"VA","votecount":1725,"votepct":0.617837,"winner":true},{"fipscode":"51115","level":"county","polid":"63881","polnum":"49277","precinctsreporting":4,"precinctsreportingpct":1,"precinctstotal":4,"raceid":"47225","statepostal":"VA","votecount":902,"votepct":0.323066,"winner":false},{"fipscode":"51115","level":"county","polid":"65898","polnum":"49354","precinctsreporting":4,"precinctsreportingpct":1,"precinctstotal":4,"raceid":"47225","statepostal":"VA","votecount":165,"votepct":0.059097,"winner":false},{"fipscode":"51117","level":"county","polid":"63126","polnum":"49283","precinctsreporting":24,"precinctsreportingpct":1,"precinctstotal":24,"raceid":"47225","statepostal":"VA","votecount":4943,"votepct":0.580846,"winner":true},{"fipscode":"51117","level":"county","polid":"63881","polnum":"49277","precinctsreporting":24,"precinctsreportingpct":1,"precinctstotal":24,"raceid":"47225","statepostal":"VA","votecount":3324,"votepct":0.390599,"winner":false},{"fipscode":"51117","level":"county","polid":"65898","polnum":"49354","precinctsreporting":24,"precinctsreportingpct":1,"precinctstotal":24,"raceid":"47225","statepostal":"VA","votecount":243,"votepct":0.028555,"winner":false},{"fipscode":"51119","level":"county","polid":"63126","polnum":"49283","precinctsreporting":7,"precinctsreportingpct":1,"precinctstotal":7,"raceid":"47225","statepostal":"VA","votecount":1763,"votepct":0.564702,"winner":true},{"fipscode":"51119","level":"county","polid":"63881","polnum":"49277","precinctsreporting":7,"precinctsreportingpct":1,"precinctstotal":7,"raceid":"47225","statepostal":"VA","votecount":1047,"votepct":0.335362,"winner":false},{"fipscode":"51119","level":"county","polid":"65898","polnum":"49354","precinctsreporting":7,"precinctsreportingpct":1,"precinctstotal":7,"raceid":"47225","statepostal":"VA","votecount":312,"votepct":0.099936,"winner":false},{"fipscode":"51121","level":"county","polid":"63126","polnum":"49283","precinctsreporting":25,"precinctsreportingpct":1,"precinctstotal":25,"raceid":"47225","statepostal":"VA","votecount":10752,"votepct":0.452202,"winner":true},{"fipscode":"51121","level":"county","polid":"63881","polnum":"49277","precinctsreporting":25,"precinctsreportingpct":1,"precinctstotal":25,"raceid":"47225","statepostal":"VA","votecount":10566,"votepct":0.444379,"winner":false},{"fipscode":"51121","level":"county","polid":"65898","polnum":"49354","precinctsreporting":25,"precinctsreportingpct":1,"precinctstotal":25,"raceid":"47225","statepostal":"VA","votecount":2459,"votepct":0.103419,"winner":false},{"fipscode":"51125","level":"county","polid":"63126","polnum":"49283","precinctsreporting":10,"precinctsreportingpct":1,"precinctstotal":10,"raceid":"47225","statepostal":"VA","votecount":2012,"votepct":0.460728,"winner":true},{"fipscode":"51125","level":"county","polid":"63881","polnum":"49277","precinctsreporting":10,"precinctsreportingpct":1,"precinctstotal":10,"raceid":"47225","statepostal":"VA","votecount":1966,"votepct":0.450195,"winner":false},{"fipscode":"51125","level":"county","polid":"65898","polnum":"49354","precinctsreporting":10,"precinctsreportingpct":1,"precinctstotal":10,"raceid":"47225","statepostal":"VA","votecount":389,"votepct":0.089077,"winner":false},{"fipscode":"51127","level":"county","polid":"63126","polnum":"49283","precinctsreporting":11,"precinctsreportingpct":1,"precinctstotal":11,"raceid":"47225","statepostal":"VA","votecount":3783,"votepct":0.626221,"winner":true},{"fipscode":"51127","level":"county","polid":"63881","polnum":"49277","precinctsreporting":11,"precinctsreportingpct":1,"precinctstotal":11,"raceid":"47225","statepostal":"VA","votecount":1642,"votepct":0.271809,"winner":false},{"fipscode":"51127","level":"county","polid":"65898","polnum":"49354","precinctsreporting":11,"precinctsreportingpct":1,"precinctstotal":11,"raceid":"47225","statepostal":"VA","votecount":616,"votepct":0.10197,"winner":false},{"fipscode":"51131","level":"county","polid":"63126","polnum":"49283","precinctsreporting":6,"precinctsreportingpct":1,"precinctstotal":6,"raceid":"47225","statepostal":"VA","votecount":1522,"votepct":0.425377,"winner":true},{"fipscode":"51131","level":"county","polid":"63881","polnum":"49277","precinctsreporting":6,"precinctsreportingpct":1,"precinctstotal":6,"raceid":"47225","statepostal":"VA","votecount":1782,"votepct":0.498044,"winner":false},{"fipscode":"51131","level":"county","polid":"65898","polnum":"49354","precinctsreporting":6,"precinctsreportingpct":1,"precinctstotal":6,"raceid":"47225","statepostal":"VA","votecount":274,"votepct":0.076579,"winner":false},{"fipscode":"51133","level":"county","polid":"63126","polnum":"49283","precinctsreporting":7,"precinctsreportingpct":1,"precinctstotal":7,"raceid":"47225","statepostal":"VA","votecount":2129,"votepct":0.560558,"winner":true},{"fipscode":"51133","level":"county","polid":"63881","polnum":"49277","precinctsreporting":7,"precinctsreportingpct":1,"precinctstotal":7,"raceid":"47225","statepostal":"VA","votecount":1401,"votepct":0.368878,"winner":false},{"fipscode":"51133","level":"county","polid":"65898","polnum":"49354","precinctsreporting":7,"precinctsreportingpct":1,"precinctstotal":7,"raceid":"47225","statepostal":"VA","votecount":268,"votepct":0.070563,"winner":false},{"fipscode":"51135","level":"county","polid":"63126","polnum":"49283","precinctsreporting":10,"precinctsreportingpct":1,"precinctstotal":10,"raceid":"47225","statepostal":"VA","votecount":1825,"votepct":0.494714,"winner":true},{"fipscode":"51135","level":"county","polid":"63881","polnum":"49277","precinctsreporting":10,"precinctsreportingpct":1,"precinctstotal":10,"raceid":"47225","statepostal":"VA","votecount":1559,"votepct":0.422608,"winner":false},{"fipscode":"51135","level":"county","polid":"65898","polnum":"49354","precinctsreporting":10,"precinctsreportingpct":1,"precinctstotal":10,"raceid":"47225","statepostal":"VA","votecount":305,"votepct":0.082678,"winner":false},{"fipscode":"51137","level":"county","polid":"63126","polnum":"49283","precinctsreporting":11,"precinctsreportingpct":1,"precinctstotal":11,"raceid":"47225","statepostal":"VA","votecount":5477,"votepct":0.580068,"winner":true},{"fipscode":"51137","level":"county","polid":"63881","polnum":"49277","precinctsreporting":11,"precinctsreportingpct":1,"precinctstotal":11,"raceid":"47225","statepostal":"VA","votecount":3230,"votepct":0.342089,"winner":false},{"fipscode":"51137","level":"county","polid":"65898","polnum":"49354","precinctsreporting":11,"precinctsreportingpct":1,"precinctstotal":11,"raceid":"47225","statepostal":"VA","votecount":735,"votepct":0.077844,"winner":false},{"fipscode":"51139","level":"county","polid":"63126","polnum":"49283","precinctsreporting":6,"precinctsreportingpct":1,"precinctstotal":6,"raceid":"47225","statepostal":"VA","votecount":3964,"votepct":0.643298,"winner":true},{"fipscode":"51139","level":"county","polid":"63881","polnum":"49277","precinctsreporting":6,"precinctsreportingpct":1,"precinctstotal":6,"raceid":"47225","statepostal":"VA","votecount":1901,"votepct":0.308504,"winner":false},{"fipscode":"51139","level":"county","polid":"65898","polnum":"49354","precinctsreporting":6,"precinctsreportingpct":1,"precinctstotal":6,"raceid":"47225","statepostal":"VA","votecount":297,"votepct":0.048199,"winner":false},{"fipscode":"51141","level":"county","polid":"63126","polnum":"49283","precinctsreporting":14,"precinctsreportingpct":1,"precinctstotal":14,"raceid":"47225","statepostal":"VA","votecount":3455,"votepct":0.721746,"winner":true},{"fipscode":"51141","level":"county","polid":"63881","polnum":"49277","precinctsreporting":14,"precinctsreportingpct":1,"precinctstotal":14,"raceid":"47225","statepostal":"VA","votecount":1165,"votepct":0.243367,"winner":false},{"fipscode":"51141","level":"county","polid":"65898","polnum":"49354","precinctsreporting":14,"precinctsreportingpct":1,"precinctstotal":14,"raceid":"47225","statepostal":"VA","votecount":167,"votepct":0.034886,"winner":false},{"fipscode":"51143","level":"county","polid":"63126","polnum":"49283","precinctsreporting":30,"precinctsreportingpct":1,"precinctstotal":30,"raceid":"47225","statepostal":"VA","votecount":11350,"votepct":0.665065,"winner":true},{"fipscode":"51143","level":"county","polid":"63881","polnum":"49277","precinctsreporting":30,"precinctsreportingpct":1,"precinctstotal":30,"raceid":"47225","statepostal":"VA","votecount":4731,"votepct":0.277218,"winner":false},{"fipscode":"51143","level":"county","polid":"65898","polnum":"49354","precinctsreporting":30,"precinctsreportingpct":1,"precinctstotal":30,"raceid":"47225","statepostal":"VA","votecount":985,"votepct":0.057717,"winner":false},{"fipscode":"51145","level":"county","polid":"63126","polnum":"49283","precinctsreporting":13,"precinctsreportingpct":1,"precinctstotal":13,"raceid":"47225","statepostal":"VA","votecount":5769,"votepct":0.689577,"winner":true},{"fipscode":"51145","level":"county","polid":"63881","polnum":"49277","precinctsreporting":13,"precinctsreportingpct":1,"precinctstotal":13,"raceid":"47225","statepostal":"VA","votecount":1766,"votepct":0.211093,"winner":false},{"fipscode":"51145","level":"county","polid":"65898","polnum":"49354","precinctsreporting":13,"precinctsreportingpct":1,"precinctstotal":13,"raceid":"47225","statepostal":"VA","votecount":831,"votepct":0.099331,"winner":false},{"fipscode":"51147","level":"county","polid":"63126","polnum":"49283","precinctsreporting":11,"precinctsreportingpct":1,"precinctstotal":11,"raceid":"47225","statepostal":"VA","votecount":2317,"votepct":0.44167,"winner":true},{"fipscode":"51147","level":"county","polid":"63881","polnum":"49277","precinctsreporting":11,"precinctsreportingpct":1,"precinctstotal":11,"raceid":"47225","statepostal":"VA","votecount":2560,"votepct":0.487991,"winner":false},{"fipscode":"51147","level":"county","polid":"65898","polnum":"49354","precinctsreporting":11,"precinctsreportingpct":1,"precinctstotal":11,"raceid":"47225","statepostal":"VA","votecount":369,"votepct":0.070339,"winner":false},{"fipscode":"51149","level":"county","polid":"63126","polnum":"49283","precinctsreporting":11,"precinctsreportingpct":1,"precinctstotal":11,"raceid":"47225","statepostal":"VA","votecount":5008,"votepct":0.563393,"winner":true},{"fipscode":"51149","level":"county","polid":"63881","polnum":"49277","precinctsreporting":11,"precinctsreportingpct":1,"precinctstotal":11,"raceid":"47225","statepostal":"VA","votecount":3294,"votepct":0.37057,"winner":false},{"fipscode":"51149","level":"county","polid":"65898","polnum":"49354","precinctsreporting":11,"precinctsreportingpct":1,"precinctstotal":11,"raceid":"47225","statepostal":"VA","votecount":587,"votepct":0.066037,"winner":false},{"fipscode":"51155","level":"county","polid":"63126","polnum":"49283","precinctsreporting":13,"precinctsreportingpct":1,"precinctstotal":13,"raceid":"47225","statepostal":"VA","votecount":5286,"votepct":0.612231,"winner":true},{"fipscode":"51155","level":"county","polid":"63881","polnum":"49277","precinctsreporting":13,"precinctsreportingpct":1,"precinctstotal":13,"raceid":"47225","statepostal":"VA","votecount":2609,"votepct":0.302177,"winner":false},{"fipscode":"51155","level":"county","polid":"65898","polnum":"49354","precinctsreporting":13,"precinctsreportingpct":1,"precinctstotal":13,"raceid":"47225","statepostal":"VA","votecount":739,"votepct":0.085592,"winner":false},{"fipscode":"51157","level":"county","polid":"63126","polnum":"49283","precinctsreporting":7,"precinctsreportingpct":1,"precinctstotal":7,"raceid":"47225","statepostal":"VA","votecount":1241,"votepct":0.537695,"winner":true},{"fipscode":"51157","level":"county","polid":"63881","polnum":"49277","precinctsreporting":7,"precinctsreportingpct":1,"precinctstotal":7,"raceid":"47225","statepostal":"VA","votecount":971,"votepct":0.420711,"winner":false},{"fipscode":"51157","level":"county","polid":"65898","polnum":"49354","precinctsreporting":7,"precinctsreportingpct":1,"precinctstotal":7,"raceid":"47225","statepostal":"VA","votecount":96,"votepct":0.041594,"winner":false},{"fipscode":"51159","level":"county","polid":"63126","polnum":"49283","precinctsreporting":6,"precinctsreportingpct":1,"precinctstotal":6,"raceid":"47225","statepostal":"VA","votecount":1194,"votepct":0.591089,"winner":true},{"fipscode":"51159","level":"county","polid":"63881","polnum":"49277","precinctsreporting":6,"precinctsreportingpct":1,"precinctstotal":6,"raceid":"47225","statepostal":"VA","votecount":705,"votepct":0.34901,"winner":false},{"fipscode":"51159","level":"county","polid":"65898","polnum":"49354","precinctsreporting":6,"precinctsreportingpct":1,"precinctstotal":6,"raceid":"47225","statepostal":"VA","votecount":121,"votepct":0.059901,"winner":false},{"fipscode":"51161","level":"county","polid":"63126","polnum":"49283","precinctsreporting":33,"precinctsreportingpct":1,"precinctstotal":33,"raceid":"47225","statepostal":"VA","votecount":16669,"votepct":0.611079,"winner":true},{"fipscode":"51161","level":"county","polid":"63881","polnum":"49277","precinctsreporting":33,"precinctsreportingpct":1,"precinctstotal":33,"raceid":"47225","statepostal":"VA","votecount":8306,"votepct":0.304494,"winner":false},{"fipscode":"51161","level":"county","polid":"65898","polnum":"49354","precinctsreporting":33,"precinctsreportingpct":1,"precinctstotal":33,"raceid":"47225","statepostal":"VA","votecount":2303,"votepct":0.084427,"winner":false},{"fipscode":"51163","level":"county","polid":"63126","polnum":"49283","precinctsreporting":18,"precinctsreportingpct":1,"precinctstotal":18,"raceid":"47225","statepostal":"VA","votecount":3210,"votepct":0.558067,"winner":true},{"fipscode":"51163","level":"county","polid":"63881","polnum":"49277","precinctsreporting":18,"precinctsreportingpct":1,"precinctstotal":18,"raceid":"47225","statepostal":"VA","votecount":2062,"votepct":0.358484,"winner":false},{"fipscode":"51163","level":"county","polid":"65898","polnum":"49354","precinctsreporting":18,"precinctsreportingpct":1,"precinctstotal":18,"raceid":"47225","statepostal":"VA","votecount":480,"votepct":0.083449,"winner":false},{"fipscode":"51165","level":"county","polid":"63126","polnum":"49283","precinctsreporting":31,"precinctsreportingpct":1,"precinctstotal":31,"raceid":"47225","statepostal":"VA","votecount":13825,"votepct":0.70774,"winner":true},{"fipscode":"51165","level":"county","polid":"63881","polnum":"49277","precinctsreporting":31,"precinctsreportingpct":1,"precinctstotal":31,"raceid":"47225","statepostal":"VA","votecount":4589,"votepct":0.234924,"winner":false},{"fipscode":"51165","level":"county","polid":"65898","polnum":"49354","precinctsreporting":31,"precinctsreportingpct":1,"precinctstotal":31,"raceid":"47225","statepostal":"VA","votecount":1120,"votepct":0.057336,"winner":false},{"fipscode":"51167","level":"county","polid":"63126","polnum":"49283","precinctsreporting":16,"precinctsreportingpct":1,"precinctstotal":16,"raceid":"47225","statepostal":"VA","votecount":4958,"votepct":0.672545,"winner":true},{"fipscode":"51167","level":"county","polid":"63881","polnum":"49277","precinctsreporting":16,"precinctsreportingpct":1,"precinctstotal":16,"raceid":"47225","statepostal":"VA","votecount":2182,"votepct":0.295985,"winner":false},{"fipscode":"51167","level":"county","polid":"65898","polnum":"49354","precinctsreporting":16,"precinctsreportingpct":1,"precinctstotal":16,"raceid":"47225","statepostal":"VA","votecount":232,"votepct":0.03147,"winner":false},{"fipscode":"51169","level":"county","polid":"63126","polnum":"49283","precinctsreporting":18,"precinctsreportingpct":1,"precinctstotal":18,"raceid":"47225","statepostal":"VA","votecount":5037,"votepct":0.774327,"winner":true},{"fipscode":"51169","level":"county","polid":"63881","polnum":"49277","precinctsreporting":18,"precinctsreportingpct":1,"precinctstotal":18,"raceid":"47225","statepostal":"VA","votecount":1254,"votepct":0.192775,"winner":false},{"fipscode":"51169","level":"county","polid":"65898","polnum":"49354","precinctsreporting":18,"precinctsreportingpct":1,"precinctstotal":18,"raceid":"47225","statepostal":"VA","votecount":214,"votepct":0.032898,"winner":false},{"fipscode":"51171","level":"county","polid":"63126","polnum":"49283","precinctsreporting":13,"precinctsreportingpct":1,"precinctstotal":13,"raceid":"47225","statepostal":"VA","votecount":7361,"votepct":0.661247,"winner":true},{"fipscode":"51171","level":"county","polid":"63881","polnum":"49277","precinctsreporting":13,"precinctsreportingpct":1,"precinctstotal":13,"raceid":"47225","statepostal":"VA","votecount":3238,"votepct":0.290873,"winner":false},{"fipscode":"51171","level":"county","polid":"65898","polnum":"49354","precinctsreporting":13,"precinctsreportingpct":1,"precinctstotal":13,"raceid":"47225","statepostal":"VA","votecount":533,"votepct":0.04788,"winner":false},{"fipscode":"51173","level":"county","polid":"63126","polnum":"49283","precinctsreporting":15,"precinctsreportingpct":1,"precinctstotal":15,"raceid":"47225","statepostal":"VA","votecount":5108,"votepct":0.676556,"winner":true},{"fipscode":"51173","level":"county","polid":"63881","polnum":"49277","precinctsreporting":15,"precinctsreportingpct":1,"precinctstotal":15,"raceid":"47225","statepostal":"VA","votecount":2114,"votepct":0.28,"winner":false},{"fipscode":"51173","level":"county","polid":"65898","polnum":"49354","precinctsreporting":15,"precinctsreportingpct":1,"precinctstotal":15,"raceid":"47225","statepostal":"VA","votecount":328,"votepct":0.043444,"winner":false},{"fipscode":"51175","level":"county","polid":"63126","polnum":"49283","precinctsreporting":14,"precinctsreportingpct":1,"precinctstotal":14,"raceid":"47225","statepostal":"VA","votecount":2548,"votepct":0.526882,"winner":true},{"fipscode":"51175","level":"county","polid":"63881","polnum":"49277","precinctsreporting":14,"precinctsreportingpct":1,"precinctstotal":14,"raceid":"47225","statepostal":"VA","votecount":2057,"votepct":0.425352,"winner":false},{"fipscode":"51175","level":"county","polid":"65898","polnum":"49354","precinctsreporting":14,"precinctsreportingpct":1,"precinctstotal":14,"raceid":"47225","statepostal":"VA","votecount":231,"votepct":0.047767,"winner":false},{"fipscode":"51177","level":"county","polid":"63126","polnum":"49283","precinctsreporting":27,"precinctsreportingpct":1,"precinctstotal":27,"raceid":"47225","statepostal":"VA","votecount":20211,"votepct":0.580592,"winner":true},{"fipscode":"51177","level":"county","polid":"63881","polnum":"49277","precinctsreporting":27,"precinctsreportingpct":1,"precinctstotal":27,"raceid":"47225","statepostal":"VA","votecount":12866,"votepct":0.369596,"winner":false},{"fipscode":"51177","level":"county","polid":"65898","polnum":"49354","precinctsreporting":27,"precinctsreportingpct":1,"precinctstotal":27,"raceid":"47225","statepostal":"VA","votecount":1734,"votepct":0.049812,"winner":false},{"fipscode":"51181","level":"county","polid":"63126","polnum":"49283","precinctsreporting":7,"precinctsreportingpct":1,"precinctstotal":7,"raceid":"47225","statepostal":"VA","votecount":844,"votepct":0.386447,"winner":true},{"fipscode":"51181","level":"county","polid":"63881","polnum":"49277","precinctsreporting":7,"precinctsreportingpct":1,"precinctstotal":7,"raceid":"47225","statepostal":"VA","votecount":1258,"votepct":0.576007,"winner":false},{"fipscode":"51181","level":"county","polid":"65898","polnum":"49354","precinctsreporting":7,"precinctsreportingpct":1,"precinctstotal":7,"raceid":"47225","statepostal":"VA","votecount":82,"votepct":0.037546,"winner":false},{"fipscode":"51183","level":"county","polid":"63126","polnum":"49283","precinctsreporting":12,"precinctsreportingpct":1,"precinctstotal":12,"raceid":"47225","statepostal":"VA","votecount":1165,"votepct":0.416816,"winner":true},{"fipscode":"51183","level":"county","polid":"63881","polnum":"49277","precinctsreporting":12,"precinctsreportingpct":1,"precinctstotal":12,"raceid":"47225","statepostal":"VA","votecount":1512,"votepct":0.540966,"winner":false},{"fipscode":"51183","level":"county","polid":"65898","polnum":"49354","precinctsreporting":12,"precinctsreportingpct":1,"precinctstotal":12,"raceid":"47225","statepostal":"VA","votecount":118,"votepct":0.042218,"winner":false},{"fipscode":"51185","level":"county","polid":"63126","polnum":"49283","precinctsreporting":25,"precinctsreportingpct":1,"precinctstotal":25,"raceid":"47225","statepostal":"VA","votecount":8429,"votepct":0.764258,"winner":true},{"fipscode":"51185","level":"county","polid":"63881","polnum":"49277","precinctsreporting":25,"precinctsreportingpct":1,"precinctstotal":25,"raceid":"47225","statepostal":"VA","votecount":2274,"votepct":0.206184,"winner":false},{"fipscode":"51185","level":"county","polid":"65898","polnum":"49354","precinctsreporting":25,"precinctsreportingpct":1,"precinctstotal":25,"raceid":"47225","statepostal":"VA","votecount":326,"votepct":0.029558,"winner":false},{"fipscode":"51187","level":"county","polid":"63126","polnum":"49283","precinctsreporting":12,"precinctsreportingpct":1,"precinctstotal":12,"raceid":"47225","statepostal":"VA","votecount":6369,"votepct":0.629721,"winner":true},{"fipscode":"51187","level":"county","polid":"63881","polnum":"49277","precinctsreporting":12,"precinctsreportingpct":1,"precinctstotal":12,"raceid":"47225","statepostal":"VA","votecount":3359,"votepct":0.332114,"winner":false},{"fipscode":"51187","level":"county","polid":"65898","polnum":"49354","precinctsreporting":12,"precinctsreportingpct":1,"precinctstotal":12,"raceid":"47225","statepostal":"VA","votecount":386,"votepct":0.038165,"winner":false},{"fipscode":"51191","level":"county","polid":"63126","polnum":"49283","precinctsreporting":20,"precinctsreportingpct":1,"precinctstotal":20,"raceid":"47225","statepostal":"VA","votecount":10207,"votepct":0.711537,"winner":true},{"fipscode":"51191","level":"county","polid":"63881","polnum":"49277","precinctsreporting":20,"precinctsreportingpct":1,"precinctstotal":20,"raceid":"47225","statepostal":"VA","votecount":3687,"votepct":0.257023,"winner":false},{"fipscode":"51191","level":"county","polid":"65898","polnum":"49354","precinctsreporting":20,"precinctsreportingpct":1,"precinctstotal":20,"raceid":"47225","statepostal":"VA","votecount":451,"votepct":0.03144,"winner":false},{"fipscode":"51193","level":"county","polid":"63126","polnum":"49283","precinctsreporting":9,"precinctsreportingpct":1,"precinctstotal":9,"raceid":"47225","statepostal":"VA","votecount":2404,"votepct":0.498755,"winner":true},{"fipscode":"51193","level":"county","polid":"63881","polnum":"49277","precinctsreporting":9,"precinctsreportingpct":1,"precinctstotal":9,"raceid":"47225","statepostal":"VA","votecount":2194,"votepct":0.455187,"winner":false},{"fipscode":"51193","level":"county","polid":"65898","polnum":"49354","precinctsreporting":9,"precinctsreportingpct":1,"precinctstotal":9,"raceid":"47225","statepostal":"VA","votecount":222,"votepct":0.046058,"winner":false},{"fipscode":"51195","level":"county","polid":"63126","polnum":"49283","precinctsreporting":13,"precinctsreportingpct":1,"precinctstotal":13,"raceid":"47225","statepostal":"VA","votecount":6705,"votepct":0.728725,"winner":true},{"fipscode":"51195","level":"county","polid":"63881","polnum":"49277","precinctsreporting":13,"precinctsreportingpct":1,"precinctstotal":13,"raceid":"47225","statepostal":"VA","votecount":2225,"votepct":0.241822,"winner":false},{"fipscode":"51195","level":"county","polid":"65898","polnum":"49354","precinctsreporting":13,"precinctsreportingpct":1,"precinctstotal":13,"raceid":"47225","statepostal":"VA","votecount":271,"votepct":0.029453,"winner":false},{"fipscode":"51197","level":"county","polid":"63126","polnum":"49283","precinctsreporting":12,"precinctsreportingpct":1,"precinctstotal":12,"raceid":"47225","statepostal":"VA","votecount":4974,"votepct":0.666488,"winner":true},{"fipscode":"51197","level":"county","polid":"63881","polnum":"49277","precinctsreporting":12,"precinctsreportingpct":1,"precinctstotal":12,"raceid":"47225","statepostal":"VA","votecount":1890,"votepct":0.253249,"winner":false},{"fipscode":"51197","level":"county","polid":"65898","polnum":"49354","precinctsreporting":12,"precinctsreportingpct":1,"precinctstotal":12,"raceid":"47225","statepostal":"VA","votecount":599,"votepct":0.080263,"winner":false},{"fipscode":"51199","level":"county","polid":"63126","polnum":"49283","precinctsreporting":14,"precinctsreportingpct":1,"precinctstotal":14,"raceid":"47225","statepostal":"VA","votecount":10584,"votepct":0.585787,"winner":true},{"fipscode":"51199","level":"county","polid":"63881","polnum":"49277","precinctsreporting":14,"precinctsreportingpct":1,"precinctstotal":14,"raceid":"47225","statepostal":"VA","votecount":6264,"votepct":0.34669,"winner":false},{"fipscode":"51199","level":"county","polid":"65898","polnum":"49354","precinctsreporting":14,"precinctsreportingpct":1,"precinctstotal":14,"raceid":"47225","statepostal":"VA","votecount":1220,"votepct":0.067523,"winner":false},{"fipscode":"51510","level":"county","polid":"63126","polnum":"49283","precinctsreporting":29,"precinctsreportingpct":1,"precinctstotal":29,"raceid":"47225","statepostal":"VA","votecount":10038,"votepct":0.244805,"winner":true},{"fipscode":"51510","level":"county","polid":"63881","polnum":"49277","precinctsreporting":29,"precinctsreportingpct":1,"precinctstotal":29,"raceid":"47225","statepostal":"VA","votecount":28997,"votepct":0.707175,"winner":false},{"fipscode":"51510","level":"county","polid":"65898","polnum":"49354","precinctsreporting":29,"precinctsreportingpct":1,"precinctstotal":29,"raceid":"47225","statepostal":"VA","votecount":1969,"votepct":0.04802,"winner":false},{"fipscode":"51520","level":"county","polid":"63126","polnum":"49283","precinctsreporting":5,"precinctsreportingpct":1,"precinctstotal":5,"raceid":"47225","statepostal":"VA","votecount":2878,"votepct":0.663286,"winner":true},{"fipscode":"51520","level":"county","polid":"63881","polnum":"49277","precinctsreporting":5,"precinctsreportingpct":1,"precinctstotal":5,"raceid":"47225","statepostal":"VA","votecount":1353,"votepct":0.311823,"winner":false},{"fipscode":"51520","level":"county","polid":"65898","polnum":"49354","precinctsreporting":5,"precinctsreportingpct":1,"precinctstotal":5,"raceid":"47225","statepostal":"VA","votecount":108,"votepct":0.024891,"winner":false},{"fipscode":"51530","level":"county","polid":"63126","polnum":"49283","precinctsreporting":2,"precinctsreportingpct":1,"precinctstotal":2,"raceid":"47225","statepostal":"VA","votecount":933,"votepct":0.598845,"winner":true},{"fipscode":"51530","level":"county","polid":"63881","polnum":"49277","precinctsreporting":2,"precinctsreportingpct":1,"precinctstotal":2,"raceid":"47225","statepostal":"VA","votecount":506,"votepct":0.324775,"winner":false},{"fipscode":"51530","level":"county","polid":"65898","polnum":"49354","precinctsreporting":2,"precinctsreportingpct":1,"precinctstotal":2,"raceid":"47225","statepostal":"VA","votecount":119,"votepct":0.07638,"winner":false},{"fipscode":"51540","level":"county","polid":"63126","polnum":"49283","precinctsreporting":10,"precinctsreportingpct":1,"precinctstotal":10,"raceid":"47225","statepostal":"VA","votecount":2197,"votepct":0.173224,"winner":true},{"fipscode":"51540","level":"county","polid":"63881","polnum":"49277","precinctsreporting":10,"precinctsreportingpct":1,"precinctstotal":10,"raceid":"47225","statepostal":"VA","votecount":9494,"votepct":0.748561,"winner":false},{"fipscode":"51540","level":"county","polid":"65898","polnum":"49354","precinctsreporting":10,"precinctsreportingpct":1,"precinctstotal":10,"raceid":"47225","statepostal":"VA","votecount":992,"votepct":0.078215,"winner":false},{"fipscode":"51550","level":"county","polid":"63126","polnum":"49283","precinctsreporting":64,"precinctsreportingpct":1,"precinctstotal":64,"raceid":"47225","statepostal":"VA","votecount":29676,"votepct":0.477697,"winner":true},{"fipscode":"51550","level":"county","polid":"63881","polnum":"49277","precinctsreporting":64,"precinctsreportingpct":1,"precinctstotal":64,"raceid":"47225","statepostal":"VA","votecount":29328,"votepct":0.472096,"winner":false},{"fipscode":"51550","level":"county","polid":"65898","polnum":"49354","precinctsreporting":64,"precinctsreportingpct":1,"precinctstotal":64,"raceid":"47225","statepostal":"VA","votecount":3119,"votepct":0.050207,"winner":false},{"fipscode":"51570","level":"county","polid":"63126","polnum":"49283","precinctsreporting":6,"precinctsreportingpct":1,"precinctstotal":6,"raceid":"47225","statepostal":"VA","votecount":3335,"votepct":0.684946,"winner":true},{"fipscode":"51570","level":"county","polid":"63881","polnum":"49277","precinctsreporting":6,"precinctsreportingpct":1,"precinctstotal":6,"raceid":"47225","statepostal":"VA","votecount":997,"votepct":0.204765,"winner":false},{"fipscode":"51570","level":"county","polid":"65898","polnum":"49354","precinctsreporting":6,"precinctsreportingpct":1,"precinctstotal":6,"raceid":"47225","statepostal":"VA","votecount":537,"votepct":0.11029,"winner":false},{"fipscode":"51580","level":"county","polid":"63126","polnum":"49283","precinctsreporting":6,"precinctsreportingpct":1,"precinctstotal":6,"raceid":"47225","statepostal":"VA","votecount":614,"votepct":0.42462,"winner":true},{"fipscode":"51580","level":"county","polid":"63881","polnum":"49277","precinctsreporting":6,"precinctsreportingpct":1,"precinctstotal":6,"raceid":"47225","statepostal":"VA","votecount":651,"votepct":0.450207,"winner":false},{"fipscode":"51580","level":"county","polid":"65898","polnum":"49354","precinctsreporting":6,"precinctsreportingpct":1,"precinctstotal":6,"raceid":"47225","statepostal":"VA","votecount":181,"votepct":0.125173,"winner":false},{"fipscode":"51590","level":"county","polid":"63126","polnum":"49283","precinctsreporting":17,"precinctsreportingpct":1,"precinctstotal":17,"raceid":"47225","statepostal":"VA","votecount":5218,"votepct":0.470769,"winner":true},{"fipscode":"51590","level":"county","polid":"63881","polnum":"49277","precinctsreporting":17,"precinctsreportingpct":1,"precinctstotal":17,"raceid":"47225","statepostal":"VA","votecount":5270,"votepct":0.47546,"winner":false},{"fipscode":"51590","level":"county","polid":"65898","polnum":"49354","precinctsreporting":17,"precinctsreportingpct":1,"precinctstotal":17,"raceid":"47225","statepostal":"VA","votecount":596,"votepct":0.053771,"winner":false},{"fipscode":"51595","level":"county","polid":"63126","polnum":"49283","precinctsreporting":8,"precinctsreportingpct":1,"precinctstotal":8,"raceid":"47225","statepostal":"VA","votecount":550,"votepct":0.367647,"winner":true},{"fipscode":"51595","level":"county","polid":"63881","polnum":"49277","precinctsreporting":8,"precinctsreportingpct":1,"precinctstotal":8,"raceid":"47225","statepostal":"VA","votecount":873,"votepct":0.583556,"winner":false},{"fipscode":"51595","level":"county","polid":"65898","polnum":"49354","precinctsreporting":8,"precinctsreportingpct":1,"precinctstotal":8,"raceid":"47225","statepostal":"VA","votecount":73,"votepct":0.048797,"winner":false},{"fipscode":"51600","level":"county","polid":"63126","polnum":"49283","precinctsreporting":7,"precinctsreportingpct":1,"precinctstotal":7,"raceid":"47225","statepostal":"VA","votecount":2613,"votepct":0.408281,"winner":true},{"fipscode":"51600","level":"county","polid":"63881","polnum":"49277","precinctsreporting":7,"precinctsreportingpct":1,"precinctstotal":7,"raceid":"47225","statepostal":"VA","votecount":3457,"votepct":0.540156,"winner":false},{"fipscode":"51600","level":"county","polid":"65898","polnum":"49354","precinctsreporting":7,"precinctsreportingpct":1,"precinctstotal":7,"raceid":"47225","statepostal":"VA","votecount":330,"votepct":0.051562,"winner":false},{"fipscode":"51610","level":"county","polid":"63126","polnum":"49283","precinctsreporting":4,"precinctsreportingpct":1,"precinctstotal":4,"raceid":"47225","statepostal":"VA","votecount":995,"votepct":0.247266,"winner":true},{"fipscode":"51610","level":"county","polid":"63881","polnum":"49277","precinctsreporting":4,"precinctsreportingpct":1,"precinctstotal":4,"raceid":"47225","statepostal":"VA","votecount":2828,"votepct":0.702783,"winner":false},{"fipscode":"51610","level":"county","polid":"65898","polnum":"49354","precinctsreporting":4,"precinctsreportingpct":1,"precinctstotal":4,"raceid":"47225","statepostal":"VA","votecount":201,"votepct":0.04995,"winner":false},{"fipscode":"51620","level":"county","polid":"63126","polnum":"49283","precinctsreporting":7,"precinctsreportingpct":1,"precinctstotal":7,"raceid":"47225","statepostal":"VA","votecount":871,"votepct":0.3837,"winner":true},{"fipscode":"51620","level":"county","polid":"63881","polnum":"49277","precinctsreporting":7,"precinctsreportingpct":1,"precinctstotal":7,"raceid":"47225","statepostal":"VA","votecount":1324,"votepct":0.58326,"winner":false},{"fipscode":"51620","level":"county","polid":"65898","polnum":"49354","precinctsreporting":7,"precinctsreportingpct":1,"precinctstotal":7,"raceid":"47225","statepostal":"VA","votecount":75,"votepct":0.03304,"winner":false},{"fipscode":"51630","level":"county","polid":"63126","polnum":"49283","precinctsreporting":6,"precinctsreportingpct":1,"precinctstotal":6,"raceid":"47225","statepostal":"VA","votecount":2565,"votepct":0.377483,"winner":true},{"fipscode":"51630","level":"county","polid":"63881","polnum":"49277","precinctsreporting":6,"precinctsreportingpct":1,"precinctstotal":6,"raceid":"47225","statepostal":"VA","votecount":3818,"votepct":0.561884,"winner":false},{"fipscode":"51630","level":"county","polid":"65898","polnum":"49354","precinctsreporting":6,"precinctsreportingpct":1,"precinctstotal":6,"raceid":"47225","statepostal":"VA","votecount":412,"votepct":0.060633,"winner":false},{"fipscode":"51640","level":"county","polid":"63126","polnum":"49283","precinctsreporting":4,"precinctsreportingpct":1,"precinctstotal":4,"raceid":"47225","statepostal":"VA","votecount":880,"votepct":0.59661,"winner":true},{"fipscode":"51640","level":"county","polid":"63881","polnum":"49277","precinctsreporting":4,"precinctsreportingpct":1,"precinctstotal":4,"raceid":"47225","statepostal":"VA","votecount":489,"votepct":0.331525,"winner":false},{"fipscode":"51640","level":"county","polid":"65898","polnum":"49354","precinctsreporting":4,"precinctsreportingpct":1,"precinctstotal":4,"raceid":"47225","statepostal":"VA","votecount":106,"votepct":0.071864,"winner":false},{"fipscode":"51650","level":"county","polid":"63126","polnum":"49283","precinctsreporting":31,"precinctsreportingpct":1,"precinctstotal":31,"raceid":"47225","statepostal":"VA","votecount":10747,"votepct":0.294406,"winner":true},{"fipscode":"51650","level":"county","polid":"63881","polnum":"49277","precinctsreporting":31,"precinctsreportingpct":1,"precinctstotal":31,"raceid":"47225","statepostal":"VA","votecount":23920,"votepct":0.655271,"winner":false},{"fipscode":"51650","level":"county","polid":"65898","polnum":"49354","precinctsreporting":31,"precinctsreportingpct":1,"precinctstotal":31,"raceid":"47225","statepostal":"VA","votecount":1837,"votepct":0.050323,"winner":false},{"fipscode":"51660","level":"county","polid":"63126","polnum":"49283","precinctsreporting":9,"precinctsreportingpct":1,"precinctstotal":9,"raceid":"47225","statepostal":"VA","votecount":4285,"votepct":0.430221,"winner":true},{"fipscode":"51660","level":"county","polid":"63881","polnum":"49277","precinctsreporting":9,"precinctsreportingpct":1,"precinctstotal":9,"raceid":"47225","statepostal":"VA","votecount":4970,"votepct":0.498996,"winner":false},{"fipscode":"51660","level":"county","polid":"65898","polnum":"49354","precinctsreporting":9,"precinctsreportingpct":1,"precinctstotal":9,"raceid":"47225","statepostal":"VA","votecount":705,"votepct":0.070783,"winner":false},{"fipscode":"51670","level":"county","polid":"63126","polnum":"49283","precinctsreporting":8,"precinctsreportingpct":1,"precinctstotal":8,"raceid":"47225","statepostal":"VA","votecount":2620,"votepct":0.471477,"winner":true},{"fipscode":"51670","level":"county","polid":"63881","polnum":"49277","precinctsreporting":8,"precinctsreportingpct":1,"precinctstotal":8,"raceid":"47225","statepostal":"VA","votecount":2473,"votepct":0.445024,"winner":false},{"fipscode":"51670","level":"county","polid":"65898","polnum":"49354","precinctsreporting":8,"precinctsreportingpct":1,"precinctstotal":8,"raceid":"47225","statepostal":"VA","votecount":464,"votepct":0.083498,"winner":false},{"fipscode":"51678","level":"county","polid":"63126","polnum":"49283","precinctsreporting":2,"precinctsreportingpct":1,"precinctstotal":2,"raceid":"47225","statepostal":"VA","votecount":562,"votepct":0.352572,"winner":true},{"fipscode":"51678","level":"county","polid":"63881","polnum":"49277","precinctsreporting":2,"precinctsreportingpct":1,"precinctstotal":2,"raceid":"47225","statepostal":"VA","votecount":970,"votepct":0.608532,"winner":false},{"fipscode":"51678","level":"county","polid":"65898","polnum":"49354","precinctsreporting":2,"precinctsreportingpct":1,"precinctstotal":2,"raceid":"47225","statepostal":"VA","votecount":62,"votepct":0.038896,"winner":false},{"fipscode":"51683","level":"county","polid":"63126","polnum":"49283","precinctsreporting":7,"precinctsreportingpct":1,"precinctstotal":7,"raceid":"47225","statepostal":"VA","votecount":4219,"votepct":0.486677,"winner":true},{"fipscode":"51683","level":"county","polid":"63881","polnum":"49277","precinctsreporting":7,"precinctsreportingpct":1,"precinctstotal":7,"raceid":"47225","statepostal":"VA","votecount":4095,"votepct":0.472373,"winner":false},{"fipscode":"51683","level":"county","polid":"65898","polnum":"49354","precinctsreporting":7,"precinctsreportingpct":1,"precinctstotal":7,"raceid":"47225","statepostal":"VA","votecount":355,"votepct":0.040951,"winner":false},{"fipscode":"51685","level":"county","polid":"63126","polnum":"49283","precinctsreporting":4,"precinctsreportingpct":1,"precinctstotal":4,"raceid":"47225","statepostal":"VA","votecount":1344,"votepct":0.436647,"winner":true},{"fipscode":"51685","level":"county","polid":"63881","polnum":"49277","precinctsreporting":4,"precinctsreportingpct":1,"precinctstotal":4,"raceid":"47225","statepostal":"VA","votecount":1596,"votepct":0.518519,"winner":false},{"fipscode":"51685","level":"county","polid":"65898","polnum":"49354","precinctsreporting":4,"precinctsreportingpct":1,"precinctstotal":4,"raceid":"47225","statepostal":"VA","votecount":138,"votepct":0.044834,"winner":false},{"fipscode":"51690","level":"county","polid":"63126","polnum":"49283","precinctsreporting":7,"precinctsreportingpct":1,"precinctstotal":7,"raceid":"47225","statepostal":"VA","votecount":1534,"votepct":0.443096,"winner":true},{"fipscode":"51690","level":"county","polid":"63881","polnum":"49277","precinctsreporting":7,"precinctsreportingpct":1,"precinctstotal":7,"raceid":"47225","statepostal":"VA","votecount":1688,"votepct":0.487579,"winner":false},{"fipscode":"51690","level":"county","polid":"65898","polnum":"49354","precinctsreporting":7,"precinctsreportingpct":1,"precinctstotal":7,"raceid":"47225","statepostal":"VA","votecount":240,"votepct":0.069324,"winner":false},{"fipscode":"51700","level":"county","polid":"63126","polnum":"49283","precinctsreporting":46,"precinctsreportingpct":1,"precinctstotal":46,"raceid":"47225","statepostal":"VA","votecount":17372,"votepct":0.373399,"winner":true},{"fipscode":"51700","level":"county","polid":"63881","polnum":"49277","precinctsreporting":46,"precinctsreportingpct":1,"precinctstotal":46,"raceid":"47225","statepostal":"VA","votecount":26597,"votepct":0.571683,"winner":false},{"fipscode":"51700","level":"county","polid":"65898","polnum":"49354","precinctsreporting":46,"precinctsreportingpct":1,"precinctstotal":46,"raceid":"47225","statepostal":"VA","votecount":2555,"votepct":0.054918,"winner":false},{"fipscode":"51710","level":"county","polid":"63126","polnum":"49283","precinctsreporting":50,"precinctsreportingpct":1,"precinctstotal":50,"raceid":"47225","statepostal":"VA","votecount":13512,"votepct":0.270809,"winner":true},{"fipscode":"51710","level":"county","polid":"63881","polnum":"49277","precinctsreporting":50,"precinctsreportingpct":1,"precinctstotal":50,"raceid":"47225","statepostal":"VA","votecount":33434,"votepct":0.670087,"winner":false},{"fipscode":"51710","level":"county","polid":"65898","polnum":"49354","precinctsreporting":50,"precinctsreportingpct":1,"precinctstotal":50,"raceid":"47225","statepostal":"VA","votecount":2949,"votepct":0.059104,"winner":false},{"fipscode":"51720","level":"county","polid":"63126","polnum":"49283","precinctsreporting":1,"precinctsreportingpct":1,"precinctstotal":1,"raceid":"47225","statepostal":"VA","votecount":543,"votepct":0.587027,"winner":true},{"fipscode":"51720","level":"county","polid":"63881","polnum":"49277","precinctsreporting":1,"precinctsreportingpct":1,"precinctstotal":1,"raceid":"47225","statepostal":"VA","votecount":346,"votepct":0.374054,"winner":false},{"fipscode":"51720","level":"county","polid":"65898","polnum":"49354","precinctsreporting":1,"precinctsreportingpct":1,"precinctstotal":1,"raceid":"47225","statepostal":"VA","votecount":36,"votepct":0.038919,"winner":false},{"fipscode":"51730","level":"county","polid":"63126","polnum":"49283","precinctsreporting":8,"precinctsreportingpct":1,"precinctstotal":8,"raceid":"47225","statepostal":"VA","votecount":966,"votepct":0.111316,"winner":true},{"fipscode":"51730","level":"county","polid":"63881","polnum":"49277","precinctsreporting":8,"precinctsreportingpct":1,"precinctstotal":8,"raceid":"47225","statepostal":"VA","votecount":7476,"votepct":0.861489,"winner":false},{"fipscode":"51730","level":"county","polid":"65898","polnum":"49354","precinctsreporting":8,"precinctsreportingpct":1,"precinctstotal":8,"raceid":"47225","statepostal":"VA","votecount":236,"votepct":0.027195,"winner":false},{"fipscode":"51735","level":"county","polid":"63126","polnum":"49283","precinctsreporting":4,"precinctsreportingpct":1,"precinctstotal":4,"raceid":"47225","statepostal":"VA","votecount":2554,"votepct":0.710431,"winner":true},{"fipscode":"51735","level":"county","polid":"63881","polnum":"49277","precinctsreporting":4,"precinctsreportingpct":1,"precinctstotal":4,"raceid":"47225","statepostal":"VA","votecount":752,"votepct":0.209179,"winner":false},{"fipscode":"51735","level":"county","polid":"65898","polnum":"49354","precinctsreporting":4,"precinctsreportingpct":1,"precinctstotal":4,"raceid":"47225","statepostal":"VA","votecount":289,"votepct":0.080389,"winner":false},{"fipscode":"51740","level":"county","polid":"63126","polnum":"49283","precinctsreporting":32,"precinctsreportingpct":1,"precinctstotal":32,"raceid":"47225","statepostal":"VA","votecount":6901,"votepct":0.277717,"winner":true},{"fipscode":"51740","level":"county","polid":"63881","polnum":"49277","precinctsreporting":32,"precinctsreportingpct":1,"precinctstotal":32,"raceid":"47225","statepostal":"VA","votecount":16551,"votepct":0.666063,"winner":false},{"fipscode":"51740","level":"county","polid":"65898","polnum":"49354","precinctsreporting":32,"precinctsreportingpct":1,"precinctstotal":32,"raceid":"47225","statepostal":"VA","votecount":1397,"votepct":0.05622,"winner":false},{"fipscode":"51750","level":"county","polid":"63126","polnum":"49283","precinctsreporting":4,"precinctsreportingpct":1,"precinctstotal":4,"raceid":"47225","statepostal":"VA","votecount":1612,"votepct":0.452555,"winner":true},{"fipscode":"51750","level":"county","polid":"63881","polnum":"49277","precinctsreporting":4,"precinctsreportingpct":1,"precinctstotal":4,"raceid":"47225","statepostal":"VA","votecount":1606,"votepct":0.45087,"winner":false},{"fipscode":"51750","level":"county","polid":"65898","polnum":"49354","precinctsreporting":4,"precinctsreportingpct":1,"precinctstotal":4,"raceid":"47225","statepostal":"VA","votecount":344,"votepct":0.096575,"winner":false},{"fipscode":"51760","level":"county","polid":"63126","polnum":"49283","precinctsreporting":67,"precinctsreportingpct":1,"precinctstotal":67,"raceid":"47225","statepostal":"VA","votecount":10754,"votepct":0.186107,"winner":true},{"fipscode":"51760","level":"county","polid":"63881","polnum":"49277","precinctsreporting":67,"precinctsreportingpct":1,"precinctstotal":67,"raceid":"47225","statepostal":"VA","votecount":42118,"votepct":0.728887,"winner":false},{"fipscode":"51760","level":"county","polid":"65898","polnum":"49354","precinctsreporting":67,"precinctsreportingpct":1,"precinctstotal":67,"raceid":"47225","statepostal":"VA","votecount":4912,"votepct":0.085006,"winner":false},{"fipscode":"51770","level":"county","polid":"63126","polnum":"49283","precinctsreporting":22,"precinctsreportingpct":1,"precinctstotal":22,"raceid":"47225","statepostal":"VA","votecount":9070,"votepct":0.374391,"winner":true},{"fipscode":"51770","level":"county","polid":"63881","polnum":"49277","precinctsreporting":22,"precinctsreportingpct":1,"precinctstotal":22,"raceid":"47225","statepostal":"VA","votecount":12951,"votepct":0.534591,"winner":false},{"fipscode":"51770","level":"county","polid":"65898","polnum":"49354","precinctsreporting":22,"precinctsreportingpct":1,"precinctstotal":22,"raceid":"47225","statepostal":"VA","votecount":2205,"votepct":0.091018,"winner":false},{"fipscode":"51775","level":"county","polid":"63126","polnum":"49283","precinctsreporting":11,"precinctsreportingpct":1,"precinctstotal":11,"raceid":"47225","statepostal":"VA","votecount":3960,"votepct":0.590957,"winner":true},{"fipscode":"51775","level":"county","polid":"63881","polnum":"49277","precinctsreporting":11,"precinctsreportingpct":1,"precinctstotal":11,"raceid":"47225","statepostal":"VA","votecount":2089,"votepct":0.311745,"winner":false},{"fipscode":"51775","level":"county","polid":"65898","polnum":"49354","precinctsreporting":11,"precinctsreportingpct":1,"precinctstotal":11,"raceid":"47225","statepostal":"VA","votecount":652,"votepct":0.097299,"winner":false},{"fipscode":"51790","level":"county","polid":"63126","polnum":"49283","precinctsreporting":6,"precinctsreportingpct":1,"precinctstotal":6,"raceid":"47225","statepostal":"VA","votecount":2938,"votepct":0.463042,"winner":true},{"fipscode":"51790","level":"county","polid":"63881","polnum":"49277","precinctsreporting":6,"precinctsreportingpct":1,"precinctstotal":6,"raceid":"47225","statepostal":"VA","votecount":2929,"votepct":0.461623,"winner":false},{"fipscode":"51790","level":"county","polid":"65898","polnum":"49354","precinctsreporting":6,"precinctsreportingpct":1,"precinctstotal":6,"raceid":"47225","statepostal":"VA","votecount":478,"votepct":0.075335,"winner":false},{"fipscode":"51800","level":"county","polid":"63126","polnum":"49283","precinctsreporting":28,"precinctsreportingpct":1,"precinctstotal":28,"raceid":"47225","statepostal":"VA","votecount":10546,"votepct":0.434707,"winner":true},{"fipscode":"51800","level":"county","polid":"63881","polnum":"49277","precinctsreporting":28,"precinctsreportingpct":1,"precinctstotal":28,"raceid":"47225","statepostal":"VA","votecount":12746,"votepct":0.525392,"winner":false},{"fipscode":"51800","level":"county","polid":"65898","polnum":"49354","precinctsreporting":28,"precinctsreportingpct":1,"precinctstotal":28,"raceid":"47225","statepostal":"VA","votecount":968,"votepct":0.039901,"winner":false},{"fipscode":"51810","level":"county","polid":"63126","polnum":"49283","precinctsreporting":99,"precinctsreportingpct":1,"precinctstotal":99,"raceid":"47225","statepostal":"VA","votecount":59858,"votepct":0.499495,"winner":true},{"fipscode":"51810","level":"county","polid":"63881","polnum":"49277","precinctsreporting":99,"precinctsreportingpct":1,"precinctstotal":99,"raceid":"47225","statepostal":"VA","votecount":52201,"votepct":0.4356,"winner":false},{"fipscode":"51810","level":"county","polid":"65898","polnum":"49354","precinctsreporting":99,"precinctsreportingpct":1,"precinctstotal":99,"raceid":"47225","statepostal":"VA","votecount":7778,"votepct":0.064905,"winner":false},{"fipscode":"51820","level":"county","polid":"63126","polnum":"49283","precinctsreporting":5,"precinctsreportingpct":1,"precinctstotal":5,"raceid":"47225","statepostal":"VA","votecount":2834,"votepct":0.55104,"winner":true},{"fipscode":"51820","level":"county","polid":"63881","polnum":"49277","precinctsreporting":5,"precinctsreportingpct":1,"precinctstotal":5,"raceid":"47225","statepostal":"VA","votecount":1878,"votepct":0.365157,"winner":false},{"fipscode":"51820","level":"county","polid":"65898","polnum":"49354","precinctsreporting":5,"precinctsreportingpct":1,"precinctstotal":5,"raceid":"47225","statepostal":"VA","votecount":431,"votepct":0.083803,"winner":false},{"fipscode":"51830","level":"county","polid":"63126","polnum":"49283","precinctsreporting":3,"precinctsreportingpct":1,"precinctstotal":3,"raceid":"47225","statepostal":"VA","votecount":1407,"votepct":0.328355,"winner":true},{"fipscode":"51830","level":"county","polid":"63881","polnum":"49277","precinctsreporting":3,"precinctsreportingpct":1,"precinctstotal":3,"raceid":"47225","statepostal":"VA","votecount":2644,"votepct":0.617036,"winner":false},{"fipscode":"51830","level":"county","polid":"65898","polnum":"49354","precinctsreporting":3,"precinctsreportingpct":1,"precinctstotal":3,"raceid":"47225","statepostal":"VA","votecount":234,"votepct":0.054609,"winner":false},{"fipscode":"51840","level":"county","polid":"63126","polnum":"49283","precinctsreporting":7,"precinctsreportingpct":1,"precinctstotal":7,"raceid":"47225","statepostal":"VA","votecount":3150,"votepct":0.502232,"winner":true},{"fipscode":"51840","level":"county","polid":"63881","polnum":"49277","precinctsreporting":7,"precinctsreportingpct":1,"precinctstotal":7,"raceid":"47225","statepostal":"VA","votecount":2794,"votepct":0.445472,"winner":false},{"fipscode":"51840","level":"county","polid":"65898","polnum":"49354","precinctsreporting":7,"precinctsreportingpct":1,"precinctstotal":7,"raceid":"47225","statepostal":"VA","votecount":328,"votepct":0.052296,"winner":false},{"fipscode":"51041","level":"county","polid":"63126","polnum":"49283","precinctsreporting":76,"precinctsreportingpct":1,"precinctstotal":76,"raceid":"47225","statepostal":"VA","votecount":48095,"votepct":0.514897,"winner":true},{"fipscode":"51041","level":"county","polid":"63881","polnum":"49277","precinctsreporting":76,"precinctsreportingpct":1,"precinctstotal":76,"raceid":"47225","statepostal":"VA","votecount":37008,"votepct":0.396202,"winner":false},{"fipscode":"51041","level":"county","polid":"65898","polnum":"49354","precinctsreporting":76,"precinctsreportingpct":1,"precinctstotal":76,"raceid":"47225","statepostal":"VA","votecount":8304,"votepct":0.088901,"winner":false},{"fipscode":"51059","level":"county","polid":"63126","polnum":"49283","precinctsreporting":244,"precinctsreportingpct":1,"precinctstotal":244,"raceid":"47225","statepostal":"VA","votecount":113621,"votepct":0.381199,"winner":true},{"fipscode":"51059","level":"county","polid":"63881","polnum":"49277","precinctsreporting":244,"precinctsreportingpct":1,"precinctstotal":244,"raceid":"47225","statepostal":"VA","votecount":170312,"votepct":0.571398,"winner":false},{"fipscode":"51059","level":"county","polid":"65898","polnum":"49354","precinctsreporting":244,"precinctsreportingpct":1,"precinctstotal":244,"raceid":"47225","statepostal":"VA","votecount":14129,"votepct":0.047403,"winner":false},{"fipscode":"51153","level":"county","polid":"63126","polnum":"49283","precinctsreporting":92,"precinctsreportingpct":1,"precinctstotal":92,"raceid":"47225","statepostal":"VA","votecount":49950,"votepct":0.458497,"winner":true},{"fipscode":"51153","level":"county","polid":"63881","polnum":"49277","precinctsreporting":92,"precinctsreportingpct":1,"precinctstotal":92,"raceid":"47225","statepostal":"VA","votecount":54907,"votepct":0.503998,"winner":false},{"fipscode":"51153","level":"county","polid":"65898","polnum":"49354","precinctsreporting":92,"precinctsreportingpct":1,"precinctstotal":92,"raceid":"47225","statepostal":"VA","votecount":4086,"votepct":0.037506,"winner":false},{"fipscode":"51179","level":"county","polid":"63126","polnum":"49283","precinctsreporting":28,"precinctsreportingpct":1,"precinctstotal":28,"raceid":"47225","statepostal":"VA","votecount":20837,"votepct":0.575083,"winner":true},{"fipscode":"51179","level":"county","polid":"63881","polnum":"49277","precinctsreporting":28,"precinctsreportingpct":1,"precinctstotal":28,"raceid":"47225","statepostal":"VA","votecount":13747,"votepct":0.379406,"winner":false},{"fipscode":"51179","level":"county","polid":"65898","polnum":"49354","precinctsreporting":28,"precinctsreportingpct":1,"precinctstotal":28,"raceid":"47225","statepostal":"VA","votecount":1649,"votepct":0.045511,"winner":false},{"fipscode":"51680","level":"county","polid":"63126","polnum":"49283","precinctsreporting":19,"precinctsreportingpct":1,"precinctstotal":19,"raceid":"47225","statepostal":"VA","votecount":11798,"votepct":0.567102,"winner":true},{"fipscode":"51680","level":"county","polid":"63881","polnum":"49277","precinctsreporting":19,"precinctsreportingpct":1,"precinctstotal":19,"raceid":"47225","statepostal":"VA","votecount":7920,"votepct":0.380696,"winner":false},{"fipscode":"51680","level":"county","polid":"65898","polnum":"49354","precinctsreporting":19,"precinctsreportingpct":1,"precinctstotal":19,"raceid":"47225","statepostal":"VA","votecount":1086,"votepct":0.052201,"winner":false}]
